<?xml version="1.0" encoding="utf-8"?>
<LanguageData>
  <!--The following translations were generated by https://www.deepl.com/-->
  <!-- EN: modern radio -->
  <ModernRadio.label>现代广播</ModernRadio.label>
  <!-- EN: A radio where you can listen to music or the RimNews. Can be placed anywere -->
  <ModernRadio.description>一个可以收听音乐或 RimNews 的收音机。可以放置在任何地方</ModernRadio.description>
  <!-- EN: radio -->
  <Radio.label>广播</Radio.label>
  <!-- EN: A radio where you can listen to music or the RimNews. -->
  <Radio.description>一个可以收听音乐或 RimNews 的电台。</Radio.description>
  <!-- EN: standing radio -->
  <StandingRadio.label>站立广播</StandingRadio.label>
  <StandingRadio.description>一个可以收听音乐或 RimNews 的电台。</StandingRadio.description>
  <!-- EN: radio on a table -->
  <TableRadio.label>桌上的收音机</TableRadio.label>
  <TableRadio.description>一个可以收听音乐或 RimNews 的电台。</TableRadio.description>
</LanguageData>
